{
    "biography": "Daily inspiration to make you smile!\n 🌈💖 Sharing the little things that brighten your day. Follow us!\n #Positivity #SmileEveryday #BrightMoments",
    "follow": 2,
    "followed": 3,
    "username": "mememosaicdaily",
    "profile_picture": "https://scontent-cdg4-1.cdninstagram.com/v/t51.2885-19/490267675_1365460407910732_2066501338964770749_n.jpg?stp=dst-jpg_s150x150_tt6&_nc_ht=scontent-cdg4-1.cdninstagram.com&_nc_cat=104&_nc_oc=Q6cZ2QGCWKaffr-wuhgW7vKPXL5kTRbkwUupyVAUpWc4ITxysV-A_EQtYi8bHfv6msoAdvG0U7yA7AG747IkzrfNNAtk&_nc_ohc=GVlHI6XY76gQ7kNvwExGtvB&_nc_gid=jNXK84tOigpqkqFvgWuQ8w&edm=AOQ1c0wBAAAA&ccb=7-5&oh=00_AfHu52mhfNXemEGg4oPu_HoOV06awOPu4hLgNlN8lT9tUg&oe=680F345A&_nc_sid=8b3546",
    "profile_picture_hd": "https://scontent-cdg4-1.cdninstagram.com/v/t51.2885-19/490267675_1365460407910732_2066501338964770749_n.jpg?stp=dst-jpg_s320x320_tt6&_nc_ht=scontent-cdg4-1.cdninstagram.com&_nc_cat=104&_nc_oc=Q6cZ2QGCWKaffr-wuhgW7vKPXL5kTRbkwUupyVAUpWc4ITxysV-A_EQtYi8bHfv6msoAdvG0U7yA7AG747IkzrfNNAtk&_nc_ohc=GVlHI6XY76gQ7kNvwExGtvB&_nc_gid=jNXK84tOigpqkqFvgWuQ8w&edm=AOQ1c0wBAAAA&ccb=7-5&oh=00_AfHu0w3f19OH9No2bn5W0eFlYc9Tm2lp3tAmklAq0afhBQ&oe=680F345A&_nc_sid=8b3546",
    "total_media": 11,
    "reel": [
        {
            "view": 0,
            "comment": 0,
            "like": 0,
            "quality": {
                "is_eligible": true,
                "number_of_qualities": 4
            }
        },
        {
            "view": 108,
            "comment": 0,
            "like": 19,
            "quality": {
                "is_eligible": true,
                "number_of_qualities": 2
            }
        },
        {
            "view": 8,
            "comment": 0,
            "like": 0,
            "quality": {
                "is_eligible": true,
                "number_of_qualities": 4
            }
        },
        {
            "view": 1,
            "comment": 0,
            "like": 0,
            "quality": {
                "is_eligible": true,
                "number_of_qualities": 2
            }
        },
        {
            "view": 211,
            "comment": 0,
            "like": 12,
            "quality": {
                "is_eligible": true,
                "number_of_qualities": 2
            }
        },
        {
            "view": 17,
            "comment": 0,
            "like": 0,
            "quality": {
                "is_eligible": true,
                "number_of_qualities": 3
            }
        },
        {
            "view": 3087,
            "comment": 13,
            "like": 595,
            "quality": {
                "is_eligible": true,
                "number_of_qualities": 3
            }
        },
        {
            "view": 1163,
            "comment": 1,
            "like": 114,
            "quality": {
                "is_eligible": true,
                "number_of_qualities": 5
            }
        },
        {
            "view": 1140,
            "comment": 0,
            "like": 95,
            "quality": {
                "is_eligible": true,
                "number_of_qualities": 3
            }
        },
        {
            "view": 795,
            "comment": 0,
            "like": 10,
            "quality": {
                "is_eligible": true,
                "number_of_qualities": 2
            }
        },
        {
            "view": 1244,
            "comment": 0,
            "like": 15,
            "quality": {
                "is_eligible": true,
                "number_of_qualities": 2
            }
        }
    ],
    "request_at": "25.04.24"
}